odoo/addons/partner_ref_sequence/LICENSE
odoo/addons/partner_ref_sequence/README.rst
odoo/addons/partner_ref_sequence/__init__.py
odoo/addons/partner_ref_sequence/__manifest__.py
odoo/addons/partner_ref_sequence/data/ir_sequence.xml
odoo/addons/partner_ref_sequence/images/screen.png
odoo/addons/partner_ref_sequence/models/__init__.py
odoo/addons/partner_ref_sequence/models/res_partner.py
odoo/addons/partner_ref_sequence/readme/CONTRIBUTORS.md
odoo/addons/partner_ref_sequence/readme/DESCRIPTION.md
odoo/addons/partner_ref_sequence/readme/USAGE.md
odoo/addons/partner_ref_sequence/static/description/icon.png
odoo/addons/partner_ref_sequence/static/description/index.html
odoo/addons/partner_ref_sequence/tests/TEST_INSTRUCTIONS.rst
odoo/addons/partner_ref_sequence/tests/__init__.py
odoo/addons/partner_ref_sequence/tests/test_partner_ref_sequence.py
odoo_addon_partner_ref_sequence-18.0.1.0.0.dist-info/METADATA
odoo_addon_partner_ref_sequence-18.0.1.0.0.dist-info/WHEEL
odoo_addon_partner_ref_sequence-18.0.1.0.0.dist-info/top_level.txt
odoo_addon_partner_ref_sequence-18.0.1.0.0.dist-info/RECORD
